{"id":"76382371","premium":false,"billing_type":{"id":"standard_plus","name":"Стандарт плюс"},"relations":[],"name":"DevOps Engineer (AWS)","insider_interview":null,"response_letter_required":false,"area":{"id":"1","name":"Москва","url":"https://api.hh.ru/areas/1?host=hh.ru"},"salary":null,"type":{"id":"open","name":"Открытая"},"address":null,"allow_messages":true,"experience":{"id":"between3And6","name":"От 3 до 6 лет"},"schedule":{"id":"fullDay","name":"Полный день"},"employment":{"id":"full","name":"Полная занятость"},"department":null,"contacts":null,"description":"<p><strong>Lesta Games</strong> ведёт разработку игровых проектов в различных жанрах, а также экспериментирует с инструментами и технологиями. Мы выпускаем легендарные игры «Мир танков», «Мир кораблей», Tanks Blitz и трудимся над новыми перспективными проектами. Наши продукты выходят на различных игровых платформах: PC, мобильные устройства.</p> <p>Мы не планируем останавливаться на достигнутом – впереди много работы, чтобы сделать наши проекты ещё более успешными.</p> <p>Офисы Lesta Games находятся в Минске, Санкт-Петербурге, Москве. У нас работают более 1700 сотрудников.</p> <p>В проект Tanks Blitz необходим талантливый <strong>DevOps Engineer</strong>, готовый поддерживать наши веб-сервисы и принять активное участие в развитии продукта в части использования облачных сервисов. Команде нужен целеустремленный участник, готовый выполнять поставленные задачи в срок.</p> <p>Вакансия преполагает работу в одном из наших офисов.</p> <p><strong>Чем предстоит заниматься:</strong></p> <ul> <li>Участвовать в поддержании и улучшении текущих CI/CD процессов.</li> <li>Разворачивать и сопровождать инфрастурктуру и приложения в AWS;</li> <li>Участвовать в разработке и проектировании решений по использованию облачных сервисов проекта Tanks Blitz.</li> <li>Обеспечивать мониторинг и аудит используемых облачных сервисов.</li> <li>Помогать в разрешении инцидентов в поддерживаемых сервисах.</li> </ul> <p><strong>Требования:</strong></p> <ul> <li>Владение инструментами IaC (Terraform).</li> <li>Опыт работы с технологиями контейнеризации (Docker).</li> <li>Знакомство с облачными технологиями и сервисами AWS.</li> <li>Опыт работы с системами мониторинга (Prometheus/Datadog).</li> <li>Знание реляционных баз данных (PostgreSQL).</li> <li>Понимание CI/CD-методологий и опыт работы с инструментами (Jenkins).</li> </ul> <p><strong>Будет плюсом:</strong></p> <ul> <li>Знание Python.</li> <li>Знакомство с технологиями оркестрации (ECS/k8s).</li> <li>Навыки быстрого поиска и устранения проблем.</li> <li>Oпыт работы с Git, понимание разных подходов.</li> <li>Базовые знания Linux (Centos/Debian).</li> </ul> <p><strong>Что предлагаем:</strong></p> <ul> <li>работу в аккредитованной IT-компании;</li> <li>расширенный полис ДМС;</li> <li>доплаты по больничным листам до 30 дней в году;</li> <li>тренажёрный зал и душевые в офисе;</li> <li>компенсацию спорта;</li> <li>компенсацию обедов;</li> <li>подарки и выплаты сотрудникам на значимые даты (первый день в компании, день рождения, свадьба, рождение детей);</li> <li>комнаты отдыха с настолками, приставками, игровыми автоматами/столами;</li> <li>релакс-зоны с массажными креслами Yamaguchi и топовыми кофемашинами;</li> <li>+ 1000 ед. игрового золота на ваш аккаунт в игре;</li> <li>work-life balance: приходим в офис (м. Савеловская) с 9 до 10, уходим с 18 до 19.</li> </ul>","branded_description":null,"vacancy_constructor_template":null,"key_skills":[{"name":"Linux"},{"name":"Git"},{"name":"Docker"},{"name":"Python"},{"name":"Terraform"},{"name":"AWS"},{"name":"Prometheus"},{"name":"CI//CD"}],"accept_handicapped":false,"accept_kids":false,"archived":false,"response_url":null,"specializations":[],"professional_roles":[{"id":"160","name":"DevOps-инженер"}],"code":null,"hidden":false,"quick_responses_allowed":false,"driver_license_types":[],"accept_incomplete_resumes":false,"employer":{"id":"856498","name":"Lesta Games","url":"https://api.hh.ru/employers/856498?host=hh.ru","alternate_url":"https://hh.ru/employer/856498","logo_urls":{"original":"https://hhcdn.ru/employer-logo-original/1002934.png","90":"https://hhcdn.ru/employer-logo/5632516.png","240":"https://hhcdn.ru/employer-logo/5632517.png"},"vacancies_url":"https://api.hh.ru/vacancies?employer_id=856498&host=hh.ru","accredited_it_employer":true,"trusted":true},"published_at":"2023-09-04T16:41:29+0300","created_at":"2023-09-04T16:41:29+0300","initial_created_at":"2023-01-30T10:58:48+0300","negotiations_url":null,"suitable_resumes_url":null,"apply_alternate_url":"https://hh.ru/applicant/vacancy_response?vacancyId=76382371","has_test":false,"test":null,"alternate_url":"https://hh.ru/vacancy/76382371","working_days":[],"working_time_intervals":[],"working_time_modes":[],"accept_temporary":false,"languages":[]}