{"id":"81285953","premium":false,"billing_type":{"id":"standard","name":"Стандарт"},"relations":[],"name":"DevOps-инженер","insider_interview":null,"response_letter_required":false,"area":{"id":"1","name":"Москва","url":"https://api.hh.ru/areas/1?host=hh.ru"},"salary":null,"type":{"id":"open","name":"Открытая"},"address":null,"allow_messages":true,"experience":{"id":"between3And6","name":"От 3 до 6 лет"},"schedule":{"id":"remote","name":"Удаленная работа"},"employment":{"id":"full","name":"Полная занятость"},"department":null,"contacts":null,"description":"<p>Компания <strong>Cinimex </strong>– разработчик ПО и системный интегратор. Мы работаем с российскими банками ТОП-20, ритейлерами, производственными и добывающими компаниями. К своему 25-летию компания имеет уникальный опыт разработки программных решений и продолжает развивать свою экспертизу: разработка на микросервисной архитектуре, машинное обучение и искусственный интеллект, IoT, продуктовое направление и автоматизация предприятий.</p> <p>Сейчас мы в поисках<strong> Devops-инженера </strong>к нам в команду!</p> <p><strong>Задачи:</strong></p> <ul> <li> <p>Настройка процесса CI/CD и сопровождение команды разработки;</p> </li> <li> <p>Разработка и доработка плейбуков развертывания;</p> </li> <li> <p>Обновление развернутых приложений;</p> </li> <li> <p>Обновление документации для группы поддержки.</p> </li> </ul> <p><strong>Ожидаем от вас:</strong></p> <ul> <li>Коммерческий опыт в области DevOps от 2 лет;</li> <li>Опыт администрирования Linux (желательно RHEL/Centos/Rocky);</li> <li>Опыт работы с CI/CD (GitLab CI, др.);</li> <li>Опыт работы с системами мониторинга (Prometheus, Grafana, Zabbix, др.);</li> <li>Опыт работы с SCM (Ansible, др.);</li> <li>Опыт работы с Kubernetes, Helm;</li> <li>Опыт работы с loki, fluentd, promtail;</li> <li>Хорошее понимание процессов сетевого взаимодействия и сетевого стека;</li> <li>Опыт развертывания БД на базе PostgreSQL; базовые знания SQL;</li> <li>Опыт написания скриптов на Bash/Python.</li> </ul> <p><strong>Плюсом будут:</strong></p> <ul> <li>Знание продуктов Hashicorp Consul и Vault;</li> <li>Понимание принципов IaC</li> </ul> <p><strong>Мы предлагаем:</strong></p> <ul> <li>Работа в аккредитованной IT-компании;</li> <li>Возможность работать удалённо или в одном из комфортных офисов;</li> <li>Гибкое начало рабочего дня: с 08:00 до 11:00;</li> <li>ДМС со стоматологией, телемедициной и полисом ВЗР;</li> <li>Возможность взять больничный без больничного: 7 дней в году;</li> <li>IT-конференции, курсы, тренинги и сертификацию за счет компании;</li> <li>Курсы английского онлайн и оффлайн с компенсацией стоимости;</li> <li>Систему фидбеков, планов развития и роста в должности/ЗП;</li> <li>Корпоративные цены в Skyeng и X-fit.</li> </ul>","branded_description":null,"vacancy_constructor_template":{"id":34616,"name":"Брендированный шаблон 4","top_picture":{"height":560,"width":1540,"path":"https://hhcdn.ru/branding-pictures/1951685.jpeg","blurred_path":"https://hhcdn.ru/branding-pictures-blurred/1951687.jpeg"},"bottom_picture":{"height":704,"width":1540,"path":"https://hhcdn.ru/branding-pictures/1952344.jpeg","blurred_path":"https://hhcdn.ru/branding-pictures-blurred/1952346.jpeg"}},"key_skills":[{"name":"Kubernetes"},{"name":"Ansible"},{"name":"Grafana"},{"name":"СУБД"},{"name":"Gitlab"},{"name":"Prometheus"},{"name":"Linux"},{"name":"PostgreSQL"},{"name":"CI/CD"},{"name":"DevOps"},{"name":"Zabbix"},{"name":"Golang"},{"name":"Python"},{"name":"Docker"},{"name":"KVM"}],"accept_handicapped":false,"accept_kids":false,"archived":false,"response_url":null,"specializations":[],"professional_roles":[{"id":"160","name":"DevOps-инженер"}],"code":null,"hidden":false,"quick_responses_allowed":false,"driver_license_types":[],"accept_incomplete_resumes":false,"employer":{"id":"6944","name":"Синимекс","url":"https://api.hh.ru/employers/6944?host=hh.ru","alternate_url":"https://hh.ru/employer/6944","logo_urls":{"90":"https://hhcdn.ru/employer-logo/2061898.png","original":"https://hhcdn.ru/employer-logo-original/404955.png","240":"https://hhcdn.ru/employer-logo/2061899.png"},"vacancies_url":"https://api.hh.ru/vacancies?employer_id=6944&host=hh.ru","accredited_it_employer":false,"trusted":true},"published_at":"2023-08-28T10:54:59+0300","created_at":"2023-08-28T10:54:59+0300","initial_created_at":"2023-05-30T10:36:34+0300","negotiations_url":null,"suitable_resumes_url":null,"apply_alternate_url":"https://hh.ru/applicant/vacancy_response?vacancyId=81285953","has_test":false,"test":null,"alternate_url":"https://hh.ru/vacancy/81285953","working_days":[],"working_time_intervals":[],"working_time_modes":[],"accept_temporary":false,"languages":[]}