{"id":"82309334","premium":false,"billing_type":{"id":"standard","name":"Стандарт"},"relations":[],"name":"Ведущий DevOps инженер [Кибербезопасность]","insider_interview":null,"response_letter_required":false,"area":{"id":"1","name":"Москва","url":"https://api.hh.ru/areas/1?host=hh.ru"},"salary":null,"type":{"id":"open","name":"Открытая"},"address":null,"allow_messages":true,"experience":{"id":"between3And6","name":"От 3 до 6 лет"},"schedule":{"id":"fullDay","name":"Полный день"},"employment":{"id":"full","name":"Полная занятость"},"department":{"id":"mts-3776-kiber","name":"«МТС» Кибербезопасность"},"contacts":null,"description":"<p>МТС RED — ки­бер­без­опас­ность, ко­то­рая действу­ет быст­рее, чем зло­у­мыш­лен­ни­ки. Мы не за­щи­ща­ем ва­ши ком­пью­те­ры или се­ти, мы за­щи­ща­ем биз­нес наших заказчиков и об­раз жиз­ни 24/7.</p> <p>Приглашаем DevOps-инженера для работы с продуктом ASOC, обеспечивающим автоматизацию процессов контроля безопасности ПО уровня Enterprise.</p> <p>Наш продукт позволяет оперировать сканерами уязвимостей (SAST, SCA, DAST и т.п.), интегрироваться в процесс разработки с системами баг-трекинга, CI/CD, хранилищами репозиториев и зависимостей, ревьюить найденные уязвимости и видеть богатую аналитику.</p> <p><strong>Чем предстоит заниматься:</strong></p> <ul> <li>работа по настройке инфраструктуры в k8s и смежным инструментам;</li> <li>подготовка дистрибутивов (в т.ч. образов Docker), написание playbook (ansible), создание/поддержка helm чартов, написание простых утилит (bash|python|golang);</li> <li>подготовка релизов, автоматизация сборки и деплой;</li> <li>поддержка нескольких окружений;</li> <li>проектирование и разработка систем мониторинга, логирования и оповещения;</li> <li>участие в разработке архитектуры продукта</li> <li>участие в работах по доставке и развертыванию продукта на стороне клиента;</li> <li>участие в тестировании и решении проблем на разных инфраструктурных уровнях;</li> <li>подготовка материалов для пользовательской и внутренней документации.</li> </ul> <p><strong>Что мы от тебя ждем:</strong></p> <ul> <li>опыт работы в сфере администрирования информационных систем и инфраструктуры – не менее 2 лет;</li> <li>знание технологий: linux, Docker, k8s, sql, bash/Python/Go;</li> <li>навыки настройки и администрирования серверов и сетевой инфраструктуры, в том числе технологий виртуализации и контейнеризации;</li> <li>опыт работы с инструментами/системами управления конфигурацией</li> <li>опыт работы с мониторингом в распределенных системах</li> <li>опыт работы с SQL/NoSQL базами данных</li> <li>опыт разработки и поддержки CI\\CD пайплайнов.</li> </ul> <p><strong>Будет плюсом:</strong></p> <ul> <li>опыт использования, конфигурации, развертывания инструментов анализа защищенности (сканеров исходного кода, динамического анализа и т.п.) и схожего класса инструментов;</li> <li>опыт работы в информационной безопасности (DevSecOps);</li> <li>понимание принципов построения архитектуры масштабируемых микросервисных продуктов;</li> <li>опыт использования систем управления конфигурацией: ansible, puppet, saltstack.</li> </ul> <p><strong>Что мы предлагаем:</strong></p> <ul> <li> <p>собственную платформу MTS Ocean для получения ИТ-ресурсов, а это значит, что деплой, мониторинг, observability - не будут для вас проблемой, вы сможете сосредоточиться на фичах;</p> </li> <li> <p>профессиональные гильдии инженеров по направлениям, чтобы поддерживать друг друга и обмениваться опытом;</p> </li> <li> <p>внутреннюю площадку TechTalks для обмена опытом, дискуссий, развития навыков самопрезентации;</p> </li> <li> <p>участие во внешних IT конференциях. Мы выступаем на HighLoad++, DataFest, Mobius, Test Driven Conf, Joker, DevOps, Матемаркетинг и даже проводим собственную конференцию по архитектуре Hello, conference!;</p> </li> <li> <p>полезные курсы и вебинары в корпоративном университете и электронные библиотеки.</p> </li> </ul> <p><strong>А еще:</strong></p> <ul> <li>компенсацию мобильной связи с первого дня;</li> <li> <p>медицинскую страховку с 1 месяца со 100% покрытием расходов, включая стоматологию, страхование жизни и здоровья в поездках за рубеж. А еще можно застраховать родственников с корпоративной скидкой;</p> </li> <li> <p>доступ к сервису «Понимаю»: онлайн-консультации с психологом, юристом, экспертом по финансам или ЗОЖ;</p> </li> <li> <p>корпоративный и командный психолог в офисе и массажный кабинет;</p> </li> <li> <p>единую подписку МТС Premium — KION light в онлайн-кинотеатре KION, сервис МТС Music, 30 дней бесплатного пользования подпиской OZON Premium;</p> </li> <li> <p>скидки и предложения от партнеров на фитнес, занятия английским и прочее;</p> </li> <li> <p>удобный формат работы - офис или гибридный (удаленно + периодические приезды в офис).</p> </li> </ul>","branded_description":null,"vacancy_constructor_template":null,"key_skills":[{"name":"Kubernetes"},{"name":"CI/CD"},{"name":"helm"},{"name":"Docker"},{"name":"Ansible"}],"accept_handicapped":false,"accept_kids":false,"archived":false,"response_url":null,"specializations":[],"professional_roles":[{"id":"160","name":"DevOps-инженер"}],"code":null,"hidden":false,"quick_responses_allowed":false,"driver_license_types":[],"accept_incomplete_resumes":false,"employer":{"id":"3776","name":"МТС","url":"https://api.hh.ru/employers/3776?host=hh.ru","alternate_url":"https://hh.ru/employer/3776","logo_urls":{"original":"https://hhcdn.ru/employer-logo-original/1077164.png","240":"https://hhcdn.ru/employer-logo/5929286.png","90":"https://hhcdn.ru/employer-logo/5929285.png"},"vacancies_url":"https://api.hh.ru/vacancies?employer_id=3776&host=hh.ru","accredited_it_employer":true,"trusted":true},"published_at":"2023-08-25T16:46:06+0300","created_at":"2023-08-25T16:46:06+0300","initial_created_at":"2023-06-22T17:43:39+0300","negotiations_url":null,"suitable_resumes_url":null,"apply_alternate_url":"https://hh.ru/applicant/vacancy_response?vacancyId=82309334","has_test":false,"test":null,"alternate_url":"https://hh.ru/vacancy/82309334","working_days":[],"working_time_intervals":[],"working_time_modes":[],"accept_temporary":false,"languages":[]}