{"id":"84954954","premium":false,"billing_type":{"id":"standard","name":"Стандарт"},"relations":[],"name":"Senior Devops Engineer","insider_interview":null,"response_letter_required":false,"area":{"id":"1","name":"Москва","url":"https://api.hh.ru/areas/1?host=hh.ru"},"salary":{"from":300000,"to":null,"currency":"RUR","gross":false},"type":{"id":"open","name":"Открытая"},"address":null,"allow_messages":true,"experience":{"id":"between3And6","name":"От 3 до 6 лет"},"schedule":{"id":"remote","name":"Удаленная работа"},"employment":{"id":"full","name":"Полная занятость"},"department":null,"contacts":null,"description":"<p><strong>Dostavista </strong>— курьерская служба доставки «последней мили». Курьеры работают через приложения для iOS и Android, доставляя более 60 тысяч отправлений ежедневно.</p> <p>Ищем Senior Devops Engineer в команду, который будет заниматься поддержкой и развитием существующей инфраструктуры.</p> <p><strong>Основные задачи: </strong></p> <ul> <li>Установка, настройка и обновление серверов с операционной системой Linux;</li> <li>Развертывание и управление контейнерами в среде Kubernetes, обеспечивая масштабируемость и отказоустойчивость системы;</li> <li>Управление и оптимизация баз данных MariaDB, Percona MySQL и PostgreSQL для обеспечения высокой производительности и доступности;</li> <li>Автоматизация процессов развертывания, мониторинга и обновления системы;</li> <li>Обеспечение безопасности системы, включая резервное копирование данных и мониторинг уязвимостей.</li> </ul> <p><strong>Пара слов о проекте</strong></p> <ul> <li>Интересные задачи, сильная команда;</li> <li>Сначала думаем, потом делаем;</li> <li>Нет проблем в коммуникациях;</li> <li>Бэкенд: MariaDB, PHP, Nginx, Redis, Clickhouse.</li> </ul> <p><strong>Необходимые навыки</strong></p> <ul> <li>Экспертные навыки администрирования Linux;</li> <li>Опыт работы с Kubernetes;</li> <li>Опыт работы с базами данных MariaDB, Percona MySQL и PostgreSQL, включая настройку, оптимизацию и резервное копирование;</li> <li>Навыки написания скриптов на bash / python;</li> <li>Навыки в автоматизации с использованием инструментов, таких как Ansible, Terraform и Docker;</li> <li>Понимание принципов IaC;</li> <li>Опыт использования инструментов CI/CD (Teamcity, Gitlab CI);</li> <li>Уверенные знания принципов построения и функционирования сетей передачи данных, основных протоколов маршрутизации и передачи данных;</li> <li>Умение и желание самостоятельно изучать и внедрять новые технологии, которые улучшают, ускоряют и упрощают процессы.</li> </ul> <p><strong>Что мы предлагаем</strong></p> <ul> <li> <p>Удаленная работа;</p> </li> <li> <p>Хорошее оборудование для работы: ноутбук, доп. монитор, гарнитура и прочее;</p> </li> <li> <p>Гибкий график: работай в удобное для тебя время. Без переработок;</p> </li> <li> <p>Полное доверие. Нет логирования времени, KPI, следящего софта и прочего;</p> </li> <li> <p>Отпуска и болезни без лишней бюрократии. Если сумма за месяц выйдет меньше твоего оклада - мы добьем разницу премией;</p> </li> <li> <p>Неформальная обстановка внутри команды;</p> </li> <li> <p>Оформление по ТК РФ, белая заработная плата;</p> </li> <li> <p>Ежегодная индексация зарплаты и обратная связь от руководителя;</p> </li> <li> <p>Помощь с карьерным ростом, если ты этого захочешь;</p> </li> <li> <p>ДМС со стоматологией и массажем.</p> </li> </ul> <p> </p>","branded_description":null,"vacancy_constructor_template":null,"key_skills":[{"name":"Linux"},{"name":"MySQL"},{"name":"Ansible"},{"name":"Docker"},{"name":"Kubernetes"},{"name":"Clickhouse"},{"name":"CI/CD"}],"accept_handicapped":false,"accept_kids":false,"archived":false,"response_url":null,"specializations":[],"professional_roles":[{"id":"160","name":"DevOps-инженер"}],"code":null,"hidden":false,"quick_responses_allowed":false,"driver_license_types":[],"accept_incomplete_resumes":false,"employer":{"id":"1316038","name":"Dostavista.ru служба доставки","url":"https://api.hh.ru/employers/1316038?host=hh.ru","alternate_url":"https://hh.ru/employer/1316038","logo_urls":{"240":"https://hhcdn.ru/employer-logo/4195269.png","90":"https://hhcdn.ru/employer-logo/4195268.png","original":"https://hhcdn.ru/employer-logo-original/938681.png"},"vacancies_url":"https://api.hh.ru/vacancies?employer_id=1316038&host=hh.ru","accredited_it_employer":false,"trusted":true},"published_at":"2023-08-23T10:30:23+0300","created_at":"2023-08-23T10:30:23+0300","initial_created_at":"2023-08-11T15:47:23+0300","negotiations_url":null,"suitable_resumes_url":null,"apply_alternate_url":"https://hh.ru/applicant/vacancy_response?vacancyId=84954954","has_test":false,"test":null,"alternate_url":"https://hh.ru/vacancy/84954954","working_days":[],"working_time_intervals":[],"working_time_modes":[],"accept_temporary":false,"languages":[]}