{"id":"85264643","premium":false,"billing_type":{"id":"standard","name":"Стандарт"},"relations":[],"name":"Senior DevOps инженер","insider_interview":null,"response_letter_required":false,"area":{"id":"1","name":"Москва","url":"https://api.hh.ru/areas/1?host=hh.ru"},"salary":null,"type":{"id":"open","name":"Открытая"},"address":{"city":"Москва","street":"5-й Донской проезд","building":"23","lat":55.701699,"lng":37.604044,"description":null,"raw":"Москва, 5-й Донской проезд, 23","metro":{"station_name":"Ленинский проспект","line_name":"Калужско-Рижская","station_id":"6.74","line_id":"6","lat":55.70678,"lng":37.58499},"metro_stations":[{"station_name":"Ленинский проспект","line_name":"Калужско-Рижская","station_id":"6.74","line_id":"6","lat":55.70678,"lng":37.58499}]},"allow_messages":true,"experience":{"id":"between3And6","name":"От 3 до 6 лет"},"schedule":{"id":"fullDay","name":"Полный день"},"employment":{"id":"full","name":"Полная занятость"},"department":null,"contacts":null,"description":"<p><strong>Что мы делаем</strong></p> <p>ОПСЛ – продуктовая компания, которая занимается разработкой быстрых игр.</p> <p>Быстрые игры UPSL — провайдер спортивных игр с большим количеством пользователей. Ежемесячно продуктом пользуются более 200 тысяч уникальных юзеров, которые делают порядка 17 миллионов ставок.</p> <p>Мы разрабатываем B2B-решение и проводим полный цикл интеграции для наших клиентов. Работаем по СНГ и выходим на новые международные рынки.</p> <p>Гибкий подход к разработке и уникальные решения — конкурентные преимущества, позволяющие привлекать все больше новых БК.</p> <p>Команда: Product Owner, Front-end Lead, Back-end Lead, DevOps, Support Managers.</p> <p> </p> <p><strong>Основные направления работы </strong></p> <ul> <li>Выполнение развертывания и обслуживания услуг отдела, в котором он участвует;</li> <li>Планирование архитектуры приложений;</li> <li>Участие в миграции;</li> <li>Разработка документации по инфраструктуре департамента;</li> <li>Принятие мер по поддержанию работоспособности приложений;</li> <li>Постановка задач по разработке модулей Terraform;</li> <li>Мониторинг текущих ресурсов;</li> <li>Консультирование коллег.</li> <li>Поддержка команды разработки;</li> <li>Принятие мер по поддержанию работоспособности приложений.</li> </ul> <p> </p> <p><strong>Профиль кандидата</strong></p> <ul> <li>5+ лет профессионального коммерческого опыта в качестве инженера DevOps;</li> <li>Обширный опыт работы с AWS и Kubernetes;</li> <li>Опыт работы c Terraform, flux;</li> <li>Сильный опыт работы с конвейерами Jenkins, Docker;</li> <li>Опыт системного администрирования Linux (bash скриптинг);</li> <li>Опыт работы с puppet (Ansible);</li> <li>Опыт работы с мониторингом (ELK, Prometheus/Grafana);</li> <li>Хорошие знания контроля исходных кодов (Git, Gitlab).</li> </ul> <p> </p> <p><strong>Культура и бенефиты:</strong></p> <ul> <li>Работаем удаленно учитывая, что онлайн-митинги назначаются с 11 до 17;</li> <li>Пользуемся 21 рабочими днями отпуска и 5 personal days в год;</li> <li>Используем Wellness Day — выходной каждая 4-я пятница месяца;</li> <li>Используем компенсацию на медицинские расходы;</li> <li>Получаем частичную компенсацию спортивных активностей;</li> <li>Используем компенсацию на обустройство рабочего места дома;</li> <li>Получаем бонусы на значимые события;</li> <li>Не используем трекеры времени, потому что ценим профессионализм и ответственность наших коллег;</li> <li>Оплачиваем большую часть профессионального обучения сотрудников;</li> <li>Получаем компенсацию английского языка;</li> <li>Возможны разные способы оформления;</li> <li>При желании можно работать из офиса в Москве (м. Ленинский проспект).</li> </ul>","branded_description":null,"vacancy_constructor_template":null,"key_skills":[{"name":"DevOps"},{"name":"Terraform"},{"name":"ELK"},{"name":"Grafana"},{"name":"Prometheus"},{"name":"Linux"},{"name":"Kubernetes"},{"name":"Docker"},{"name":"AWS"},{"name":"Jenkins"},{"name":"Администрирование серверов Linux"},{"name":"Gitlab"},{"name":"Golang"},{"name":"ClickHouse"}],"accept_handicapped":false,"accept_kids":false,"archived":false,"response_url":null,"specializations":[],"professional_roles":[{"id":"160","name":"DevOps-инженер"}],"code":null,"hidden":false,"quick_responses_allowed":false,"driver_license_types":[],"accept_incomplete_resumes":false,"employer":{"id":"9487849","name":"Объединенная Профессиональная Спортивная Лига","url":"https://api.hh.ru/employers/9487849?host=hh.ru","alternate_url":"https://hh.ru/employer/9487849","logo_urls":{"240":"https://hhcdn.ru/employer-logo/5812926.jpeg","90":"https://hhcdn.ru/employer-logo/5812925.jpeg","original":"https://hhcdn.ru/employer-logo-original/1048068.jpeg"},"vacancies_url":"https://api.hh.ru/vacancies?employer_id=9487849&host=hh.ru","accredited_it_employer":false,"trusted":true},"published_at":"2023-08-17T16:16:58+0300","created_at":"2023-08-17T16:16:58+0300","initial_created_at":"2023-08-17T16:16:58+0300","negotiations_url":null,"suitable_resumes_url":null,"apply_alternate_url":"https://hh.ru/applicant/vacancy_response?vacancyId=85264643","has_test":false,"test":null,"alternate_url":"https://hh.ru/vacancy/85264643","working_days":[],"working_time_intervals":[],"working_time_modes":[],"accept_temporary":false,"languages":[]}