{"id":"85467543","premium":false,"billing_type":{"id":"standard","name":"Стандарт"},"relations":[],"name":"DevOps-инженер","insider_interview":null,"response_letter_required":false,"area":{"id":"1","name":"Москва","url":"https://api.hh.ru/areas/1?host=hh.ru"},"salary":null,"type":{"id":"open","name":"Открытая"},"address":{"city":null,"street":null,"building":null,"lat":null,"lng":null,"description":null,"raw":null,"metro":{"station_name":"Чистые пруды","line_name":"Сокольническая","station_id":"1.143","line_id":"1","lat":55.76499,"lng":37.638293},"metro_stations":[{"station_name":"Чистые пруды","line_name":"Сокольническая","station_id":"1.143","line_id":"1","lat":55.76499,"lng":37.638293}]},"allow_messages":true,"experience":{"id":"between3And6","name":"От 3 до 6 лет"},"schedule":{"id":"fullDay","name":"Полный день"},"employment":{"id":"full","name":"Полная занятость"},"department":null,"contacts":null,"description":"<strong>Обязанности:</strong> <ul> <li>Курирование нескольких бизнес систем самостоятельно или совместно с коллегами, с т.зр. решения перечисленных ниже задач.</li> <li>Планирование, создание и сопровождение dev/test/qa сред совместно с профильными специалистами по системному и прикладному, платформенному ПО, DBA.</li> <li>Размещение стандартных задач в специализированные ИТ-службы (виртуализация, ОС, СУБД, СХД, сети, учетные записи, ИБ, мониторинг и проч.)</li> <li>Управление конфигурациями, ведение технических описаний (паспортов) продуктивных и непродуктивных сред.</li> <li>Участие в совершенствовании практик мониторинга.<br />Участие в развитии процессов CI/CD.</li> <li>Инженерная поддержка развитию и проведению автотестирования (функциональное, производительности).</li> </ul> <strong>Требования:</strong> <ul> <li>Практический опыт: Jenkins, HTTP monitoring, Docker, Selenoid</li> <li>Практический опыт желательно (плюсом, любой уровень): Windows Server, Linux, PostgreSQL/PostgrePro/Oracle DB, Tomcat, PowerShell, bash, RDP, Artifactory, Nexus, JMeter, Selenium, снифферы, Git, Jira, Confluence, BitBucket</li> <li>Будет плюсом кругозор: Grafana, Zabbix, Moon, TestIT, LoadIT, ТестОпс</li> <li>Высшее техническое образование</li> </ul> <strong>Условия:</strong> <ul> <li>Возможна работа удаленно или гибридный формат (строго на территории РФ).</li> <li>Бессрочный трудовой договор.</li> <li>Строгое соблюдение ТК РФ.</li> <li>Стабильная «белая» заработная плата.</li> <li>Отпуск – 28 дней.</li> <li>Производится выплата премии к профессиональному празднику.</li> <li>Годовое вознаграждение (13 заработная плата).</li> <li>Материальная помощь к отпуску.</li> <li>Индексация заработной платы в зависимости от инфляции.</li> <li>Аккредитованная ИТ-компания ООО &quot;ЛУКОЙЛ-Технологии&quot;</li> <li>Медицинская страховка</li> <li>Испытательный срок 3 мес.</li> </ul>","branded_description":null,"vacancy_constructor_template":null,"key_skills":[],"accept_handicapped":true,"accept_kids":false,"archived":false,"response_url":null,"specializations":[],"professional_roles":[{"id":"160","name":"DevOps-инженер"}],"code":null,"hidden":false,"quick_responses_allowed":false,"driver_license_types":[],"accept_incomplete_resumes":false,"employer":{"id":"907345","name":"ЛУКОЙЛ","url":"https://api.hh.ru/employers/907345?host=hh.ru","alternate_url":"https://hh.ru/employer/907345","logo_urls":{"240":"https://hhcdn.ru/employer-logo/790401.png","90":"https://hhcdn.ru/employer-logo/790400.png","original":"https://hhcdn.ru/employer-logo-original/114544.png"},"vacancies_url":"https://api.hh.ru/vacancies?employer_id=907345&host=hh.ru","accredited_it_employer":false,"trusted":true},"published_at":"2023-08-21T16:20:12+0300","created_at":"2023-08-21T16:20:12+0300","initial_created_at":"2023-08-21T16:20:12+0300","negotiations_url":null,"suitable_resumes_url":null,"apply_alternate_url":"https://hh.ru/applicant/vacancy_response?vacancyId=85467543","has_test":false,"test":null,"alternate_url":"https://hh.ru/vacancy/85467543","working_days":[],"working_time_intervals":[],"working_time_modes":[],"accept_temporary":false,"languages":[]}